Workbook

Sheet 1. Supuestos & Macro
A1: Parámetro / Variable Macroeconómica | B1: Símbolo | C1: Valor Asumido | D1: Unidad / Formato | E1: Fuente Oficial / Fundamento Técnico
A2: Horizonte Temporal de Evaluación | B2: N | C2: 4 | D2: Años | E2: Estándar para evaluación de proyectos de software y plataformas SaaS
A3: Año 0: Constitución & Desarrollo Pre-operativo (2 Socios) | B3: Año 0 | C3: 2026 | D3: Año | E3: Fase de arquitectura, programación del MVP y pruebas de terreno
A4: Año 1: Lanzamiento Comercial & Operación Inicial | B4: Año 1 | C4: 2027 | D4: Año | E4: Comienzo de operaciones comerciales y primeros 95 clientes activos
A5: Año 2: Crecimiento y Consolidación Regional | B5: Año 2 | C5: 2028 | D5: Año | E5: Consolidación en Región Metropolitana (210 clientes activos)
A6: Año 3: Expansión Nacional | B6: Año 3 | C6: 2029 | D6: Año | E6: Expansión a principales zonas constructoras del país (380 clientes activos)
A7: Año 4: Madurez del Software & Cobertura Integral | B7: Año 4 | C7: 2030 | D7: Año | E7: Liderazgo en gestión digital de obras para PYMEs (580 clientes activos)
A8: Tasa de Inflación Anual Proyectada (IPC) | B8: IPC | C8: 0.038 | D8: 3.80% | E8: Rango meta de largo plazo del Banco Central de Chile (3.0% - 4.0%)
A9: Impuesto a la Renta de 1ª Categoría (SII) | B9: Tc | C9: 0.27 | D9: 27.00% | E9: Servicio de Impuestos Internos (SII) - Régimen General corporativo
A10: Tipo de Cambio Nominal Proyectado | B10: USD/CLP | C10: 940 | D10: CLP / USD | E10: Promedio proyectado Banco Central de Chile
A11: Tasa Libre de Riesgo (Depósito a Plazo) | B11: Rf | C11: 0.04 | D11: 4.00% | E11: Tasa de Interés Depósito a Plazo BancoEstado / Banco Central (Recomendación Prof. Patricia)
A12: Beta Sectorial Software & SaaS (Damodaran) | B12: β | C12: 1.25 | D12: 1.25 | E12: Aswath Damodaran (NYU Stern) - Software (System & Application)
A13: Prima por Riesgo de Mercado Accionario (Rm - Rf) | B13: PRM | C13: 0.06 | D13: 6.00% | E13: Diferencial exigido por inversionistas sobre el activo libre de riesgo
A14: Riesgo País de Chile (Indicador EMBI JP Morgan) | B14: Rp | C14: 0.0135 | D14: 1.35% | E14: Riesgo soberano de Chile (aprox. 135 puntos base)
A15: Tasa de Descuento Anual (CAPM: Ke = Rf + β*PRM + Rp) | B15: Ke | C15: =C11+C12*C13+C14 -> 0.1285 | D15: 12.85% | E15: Costo de Oportunidad del Capital (Rango 11% - 15% solicitado por Prof. Patricia)
A16: Vida Útil Tributaria Equipos Computacionales | B16: VU_TI | C16: 3 | D16: Años | E16: Tabla Oficial de Vida Útil de Bienes Físicos del SII
A17: Vida Útil Smartphones para Test de Terreno | B17: VU_MOB | C17: 2 | D17: Años | E17: Tabla Oficial de Vida Útil de Bienes Físicos del SII
A18: Comisión Pasarela Transbank Webpay Plus | B18: C_PAY | C18: 0.025 | D18: 2.50% | E18: Arancel comercial Transbank Webpay Plus sobre ventas netas
A19: Comisión por Venta a Ejecutivos Comerciales | B19: C_VTA | C19: 0.05 | D19: 5.00% | E19: Incentivo comercial variable sobre facturación neta
A21: MARCO TEÓRICO Y CONCEPTUAL DE EVALUACIÓN DE PROYECTOS (RESPUESTAS A PROFESORA PATRICIA)
A22: 1. ¿Qué es el Capital de Trabajo (KT) y cómo se calcula? | B22: Definición: | C22: Es el volumen de recursos financieros líquidos que la empresa debe disponer anticipadamente para cubrir el desfase temporal entre el pago de egresos operacionales (sueldos, licencias, nube, arriendo) y la recaudación efectiva de ingresos por ventas de suscripciones.
A23: ¿Por qué se invierte en Año 0 y se recupera en Año 4? | B23: Justificación: | C23: En el Año 0 se invierte para financiar los 6 meses de desarrollo de los 2 fundadores y los meses iniciales con desfase de caja. En el Año 4 se recupera íntegramente al 100% porque el Capital de Trabajo no es un costo ni un gasto consumido, sino un fondo de maniobra rotativo que queda liberado y disponible al liquidar el horizonte del proyecto.
A24: 2. ¿Qué es la Tasa de Descuento (Ke) y cómo se calcula? | B24: Definición: | C24: Representa el costo de oportunidad del dinero: la rentabilidad mínima que los inversionistas le exigen a ObraTrack SpA frente a alternativas de riesgo similar. Se calculó rigurosamente mediante el modelo CAPM con la tasa de depósito a plazo (4.0%), beta sectorial de software (1.25), prima de riesgo de mercado (6.0%) y riesgo país (1.35%): Ke = 4.0% + 1.25*6.0% + 1.35% = 12.85%, cumpliendo estrictamente con el rango de 11% a 15% solicitado.

Sheet 2. Mano de Obra
A1: SECCIÓN A: MANO DE OBRA EN AÑO 0 (DESARROLLO PRE-OPERATIVO - 2 FUNDADORES, 6 MESES)
A2: Rol / Cargo del Equipo | B2: Modalidad | C2: Cant. | D2: Sueldo Bruto Mes (CLP) | E2: Leyes Soc. (4.5%) | F2: Año 0 (2026) | G2: Año 1 (2027) | H2: Año 2 (2028) | I2: Año 3 (2029) | J2: Año 4 (2030)
A3: Fundador 1: Benjamín Achávar (Lead Architect / Dev) | B3: Pre-operativo (6 Meses) | C3: 1 | D3: 700000 | E3: =D3*0.045 -> 31500 | F3: =C3*(D3+E3)*6 -> 4389000 | G3: 0 | H3: 0 | I3: 0 | J3: 0
A4: Fundador 2: Co-Fundador (Full-Stack Dev & QA) | B4: Pre-operativo (6 Meses) | C4: 1 | D4: 700000 | E4: =D4*0.045 -> 31500 | F4: =C4*(D4+E4)*6 -> 4389000 | G4: 0 | H4: 0 | I4: 0 | J4: 0
A5: Subtotal Mano de Obra Año 0 (Inversión Capital de Trabajo) | B5: - | C5: 2 | D5: =SUM(D3:D4) -> 1400000 | E5: =SUM(E3:E4) -> 63000 | F5: =SUM(F3:F4) -> 8778000 | G5: 0 | H5: 0 | I5: 0 | J5: 0
A7: SECCIÓN B: MANO DE OBRA OPERATIVA (AÑOS 1 AL 4: FUNDADORES + EQUIPO DE ESCALAMIENTO)
A8: Rol / Cargo del Equipo | B8: Modalidad | C8: Cant. | D8: Sueldo Bruto Mes (CLP) | E8: Leyes Soc. (4.5%) | F8: Año 0 (2026) | G8: Año 1 (2027) | H8: Año 2 (2028) | I8: Año 3 (2029) | J8: Año 4 (2030)
A9: Fundador 1: Jefe de Proyecto & CTO | B9: Indefinido (Jornada Completa) | C9: 1 | D9: 650000 | E9: =D9*0.045 -> 29250 | F9: 0 | G9: =C9*(D9+E9)*12 -> 8151000 | H9: =C9*(800000*(1+0.045))*12 -> 10032000 | I9: =C9*(950000*(1+0.045))*12 -> 11913000 | J9: =C9*(1150000*(1+0.045))*12 -> 14421000
A10: Fundador 2: Desarrollador Full-Stack Senior | B10: Indefinido (Jornada Completa) | C10: 1 | D10: 650000 | E10: =D10*0.045 -> 29250 | F10: 0 | G10: =C10*(D10+E10)*12 -> 8151000 | H10: =C10*(800000*(1+0.045))*12 -> 10032000 | I10: =C10*(950000*(1+0.045))*12 -> 11913000 | J10: =C10*(1150000*(1+0.045))*12 -> 14421000
A11: Soporte Técnico & Onboarding Terreno (Ingreso Año 2) | B11: Indefinido (Onboarding y Faenas) | C11: 1 | D11: 500000 | E11: =D11*0.045 -> 22500 | F11: 0 | G11: 0 | H11: =C11*(D11+E11)*12 -> 6270000 | I11: =C11*(550000*(1+0.045))*12 -> 6897000 | J11: =C11*(600000*(1+0.045))*12 -> 7524000
A12: Ejecutivo Comercial B2B (Ingreso Año 3) | B12: Indefinido (Sueldo Base) | C12: 1 | D12: 550000 | E12: =D12*0.045 -> 24750 | F12: 0 | G12: 0 | H12: 0 | I12: =C12*(D12+E12)*12 -> 6897000 | J12: =C12*(600000*(1+0.045))*12 -> 7524000
A13: Total Sueldos Fijos Fase Operativa (CLP) | B13: - | C13: =SUM(C9:C12) -> 4 | D13: - | E13: - | F13: 0 | G13: =SUM(G9:G12) -> 16302000 | H13: =SUM(H9:H12) -> 26334000 | I13: =SUM(I9:I12) -> 37620000 | J13: =SUM(J9:J12) -> 43890000

Sheet 3. Maquinaria & Equipos
A1: BALANCE DE MAQUINARIA Y EQUIPAMIENTO (INVERSIÓN EN AÑO 0 Y ADQUISICIÓN EN AÑO 1)
A2: Detalle del Activo Fijo | B2: Momento Compra | C2: Cant. | D2: Precio Unitario Sin IVA | E2: Inversión Total Sin IVA | F2: Vida Útil (SII) | G2: Depreciación Anual | H2: Valor Residual Total | I2: Usuario Asignado / Rol
A3: PC Escritorio Desarrollo Profesional (Core i7, 32GB) | B3: Año 0 (Aporte Socio) | C3: 1 | D3: 850000 | E3: =C3*D3 -> 850000 | F3: 3 | G3: =(E3-H3)/F3 -> 255000 | H3: 85000 | I3: Benjamín Achávar (Estación de trabajo)
A4: Notebook Desarrollo Co-Fundador (ThinkPad/Dell 32GB) | B4: Año 0 (Aporte Socio) | C4: 1 | D4: 950000 | E4: =C4*D4 -> 950000 | F4: 3 | G4: =(E4-H4)/F4 -> 285000 | H4: 95000 | I4: Co-Fundador (Desarrollo y DevOps)
A5: Smartphone Android Test Terreno (Samsung A35 Movistar) | B5: Año 0 (Compra Inicial) | C5: 1 | D5: 180000 | E5: =C5*D5 -> 180000 | F5: 2 | G5: =(E5-H5)/F5 -> 80000 | H5: 20000 | I5: Pruebas de GPS, fotos faena y WhatsApp
A6: Monitores Profesionales 27" IPS (2 Estaciones) | B6: Año 0 (Compra Inicial) | C6: 2 | D6: 150000 | E6: =C6*D6 -> 300000 | F6: 3 | G6: =(E6-H6)/F6 -> 90000 | H6: 30000 | I6: Productividad de programación dual
A7: Notebook Soporte Técnico & Onboarding en Obra | B7: Año 1 (Adquisición) | C7: 1 | D7: 750000 | E7: =C7*D7 -> 750000 | F7: 3 | G7: =(E7-H7)/F7 -> 225000 | H7: 75000 | I7: Personal de Soporte Técnico Terreno
A8: Smartphone Terreno Adicional para Cuadrillas | B8: Año 1 (Adquisición) | C8: 1 | D8: 150000 | E8: =C8*D8 -> 150000 | F8: 2 | G8: =(E8-H8)/F8 -> 67500 | H8: 15000 | I8: Soporte y visitas técnicas a faena
A9: Subtotal Inversión Maquinaria en Año 0 (Activo Fijo Inicial) | B9: - | C9: =SUM(C3:C6) -> 5 | D9: - | E9: =SUM(E3:E6) -> 2280000 | F9: - | G9: =SUM(G3:G6) -> 710000 | H9: =SUM(H3:H6) -> 230000 | I9: Inversión Inicial en Hardware
A10: Subtotal Inversión Maquinaria en Año 1 (Reinversión / Nuevo Personal) | B10: - | C10: =SUM(C7:C8) -> 2 | D10: - | E10: =SUM(E7:E8) -> 900000 | F10: - | G10: =SUM(G7:G8) -> 292500 | H10: =SUM(H7:H8) -> 90000 | I10: Inversión de Expansión en Año 1
A12: CALENDARIO DE DEPRECIACIÓN TRIBUTARIA (SII) | C12: Año 0 (2026) | D12: Año 1 (2027) | E12: Año 2 (2028) | F12: Año 3 (2029) | G12: Año 4 (2030) | H12: Valor Libro Final | I12: Valor Desecho Estimado
A13: Depreciación Lote Año 0 (3 años equipos, 2 años smart) | C13: 0 | D13: 710000 | E13: 710000 | F13: 630000 | G13: 0 | H13: 230000 | I13: 230000
A14: Depreciación Lote Año 1 (3 años notebook, 2 años smart) | C14: 0 | D14: 292500 | E14: 292500 | F14: 225000 | G14: 225000 | H14: 90000 | I14: 90000
A15: Depreciación Total por Período (CLP) | C15: 0 | D15: =SUM(D13:D14) -> 1002500 | E15: =SUM(E13:E14) -> 1002500 | F15: =SUM(F13:F14) -> 855000 | G15: =SUM(G13:G14) -> 225000 | H15: =SUM(H13:H14) -> 320000 | I15: =SUM(I13:I14) -> 320000

Sheet 4. Software & Licencias
A1: BALANCE DE SOFTWARE, LICENCIAS Y CONECTIVIDAD (AÑO 0 DESARROLLO VS AÑOS 1-4 PRODUCCIÓN)
A2: Herramienta Tecnológica | B2: Modalidad | C2: Costo USD | D2: Año 0 (Desarrollo) | E2: Año 1 (2027) | F2: Año 2 (2028) | G2: Año 3 (2029) | H2: Año 4 (2030) | I2: Proveedor / Justificación Técnica
A3: Google AI Pro Estudiante (Plan $5.400/mes) | B3: Mensual x 12 (Benjamín) | C3: 0 | D3: 64800 | E3: 64800 | F3: 67262 | G3: 69818 | H3: 72471 | I3: Suscripción personal Google AI para desarrollo
A4: Plan Datos Móviles Smartphone Movistar | B4: Mensual x 12 (Conexión) | C4: 0 | D4: 179880 | E4: 179880 | F4: 186715 | G4: 193811 | H4: 201175 | I4: Conectividad 4G/5G para pruebas en faena
A5: Dominio Oficial .CL (NIC Chile) | B5: Anual | C5: 0 | D5: 9950 | E5: 9950 | F5: 10328 | G5: 10721 | H5: 11128 | I5: NIC Chile (Universidad de Chile)
A6: Cuenta Google Play Developer | B6: Pago Único Inicial | C6: 25 | D6: 23500 | E6: 0 | F6: 0 | G6: 0 | H6: 0 | I6: Google Play Console (Publicación Android)
A7: Apple Developer Program (iOS App) | B7: Anual | C7: 99 | D7: 93060 | E7: 93060 | F7: 96596 | G7: 100267 | H7: 104077 | I7: Apple Developer Enterprise
A8: GitHub Team & Copilot Workspace (2 Devs) | B8: Mensual x 12 | C8: 38 | D8: 214320 | E8: 428640 | F8: 444928 | G8: 461836 | H8: 479385 | I8: Licencias GitHub para desarrollo colaborativo
A9: Vercel (Hosting & Edge Functions Next.js) | B9: Free en Año 0 -> Pro en Año 1 | C9: 20 | D9: 0 | E9: 225600 | F9: 234173 | G9: 243071 | H9: 252308 | I9: Despliegue CI/CD, SSL y SSR global Next.js
A10: Supabase (PostgreSQL, Auth & Storage Faena) | B10: Free en Año 0 -> Pro en Año 1 | C10: 25 | D10: 0 | E10: 282000 | F10: 507600 | G10: 902400 | H10: 1466400 | I10: Escala con gigabytes de fotos de faena y backups
A11: Total Software, Licencias & Conectividad (CLP) | B11: - | C11: - | D11: =SUM(D3:D10) -> 585510 | E11: =SUM(E3:E10) -> 1283930 | F11: =SUM(F3:F10) -> 1547602 | G11: =SUM(G3:G10) -> 1981924 | H11: =SUM(H3:H10) -> 2586944 | I11: Herramientas Tecnológicas del Proyecto

Sheet 5. Infraestructura Cloud
A1: Servicio Cloud / API Externa | B1: Métrica de Consumo / Plan | C1: Año 1 (2027) | D1: Año 2 (2028) | E1: Año 3 (2029) | F1: Año 4 (2030) | G1: Justificación Técnica de Escalabilidad
A2: Google Gemini API (3.5/3.6/2.5 Flash) | B2: Tokens de Cotizador, APU y Chat | C2: 420000 | D2: 1050000 | E2: 2100000 | F2: 3480000 | G2: Inferencia de cubicaciones y radar de ferreterías
A3: WhatsApp Business Cloud API (Meta) | B3: Notificaciones de Avance y Reportes | C3: 480000 | D3: 1200000 | E3: 2400000 | F3: 3960000 | G3: Costo por conversación iniciada con mandantes
A4: Google Maps Platform (Geocoding) | B4: GPS Faenas y Reverse Geocoding | C4: 0 | D4: 80000 | E4: 160000 | F4: 260000 | G4: Primeros 28.500 llamados cubiertos por crédito $200 USD
A5: Servicios de Respaldo y Telemetría | B5: Monitoreo Sentry & Backups diarios | C5: 96000 | D5: 120000 | E5: 180000 | F5: 240000 | G5: Monitoreo de excepciones y respaldos off-site
A6: Total Consumo Cloud & APIs en Producción (CLP) | B6: Costo Variable Directo | C6: =SUM(C2:C5) -> 996000 | D6: =SUM(D2:D5) -> 2450000 | E6: =SUM(E2:E5) -> 4840000 | F6: =SUM(F2:F5) -> 7940000 | G6: Costo Tecnológico Directo según Obras Activas

Sheet 6. Insumos & Gastos Gen
A1: Concepto de Gasto Operacional | B1: Modalidad de Contratación | C1: Año 0 (2026) | D1: Año 1 (2027) | E1: Año 2 (2028) | F1: Año 3 (2029) | G1: Año 4 (2030) | H1: Detalle / Proveedor Seleccionado
A2: Constitución de Sociedad SpA (Firma/Notaría) | B2: Gasto Pre-operativo Único | C2: 180000 | D2: 0 | E2: 0 | F2: 0 | G2: 0 | H2: Formalización legal en Tu Empresa en un Día
A3: Registro de Marca ObraTrack en INAPI | B3: Gasto Pre-operativo Único | C3: 320000 | D3: 0 | E3: 0 | F3: 0 | G3: 0 | H3: Protección de propiedad intelectual (Clases 9 y 42)
A4: Oficina Virtual y Domicilio Tributario | B4: Mensual (Virtual Pyme / Providencia) | C4: 0 | D4: 288000 | E4: =D4*(1+'1. Supuestos & Macro'!C8) -> 298944 | F4: =E4*(1+'1. Supuestos & Macro'!C8) -> 310304 | G4: =F4*(1+'1. Supuestos & Macro'!C8) -> 322095 | H4: Dirección comercial, recepción SII y patentes
A5: Outsourcing Contable & Tributario (Contador) | B5: Mensual (Estudio Contable PYME) | C5: 0 | D5: 840000 | E5: =D5*(1+'1. Supuestos & Macro'!C8) -> 871920 | F5: =E5*(1+'1. Supuestos & Macro'!C8) -> 905053 | G5: =F5*(1+'1. Supuestos & Macro'!C8) -> 939445 | H5: Declaraciones mensuales F29, Balance y Renta SII
A6: Gastos de Visitas Técnicas & Terreno (Transporte) | B6: Mensual (Combustible / Movilización) | C6: 0 | D6: 720000 | E6: 1020000 | F6: 1320000 | G6: 1680000 | H6: Visitas de onboarding a faenas y capataces
A7: Insumos de Oficina, Red & Papelería Técnica | B7: Mensual | C7: 0 | D7: 300000 | E7: =D7*(1+'1. Supuestos & Macro'!C8) -> 311400 | F7: =E7*(1+'1. Supuestos & Macro'!C8) -> 323233 | G7: =F7*(1+'1. Supuestos & Macro'!C8) -> 335516 | H7: Material corporativo, folletería de faena
A8: Total Insumos & Gastos Generales (CLP) | B8: Gastos Administrativos | C8: =SUM(C2:C3) -> 500000 | D8: =SUM(D4:D7) -> 2148000 | E8: =SUM(E4:E7) -> 2502264 | F8: =SUM(F4:F7) -> 2858590 | G8: =SUM(G4:G7) -> 3277056 | H8: Gastos Operacionales y Pre-operativos

Sheet 7. Demanda & Ingresos
A1: Línea de Servicio / Plan Comercial | B1: Mix Ventas (%) | C1: Precio Mensual Neto (CLP) | D1: Año 1 (2027) | E1: Año 2 (2028) | F1: Año 3 (2029) | G1: Año 4 (2030)
A2: Plan Gratis (1 Obra activa, Freemium permanente) | B2: 0 | C2: 0 | D2: - | E2: - | F2: - | G2: -
A3: Plan Pro ($9.990 - $14.990 / Obras ilimitadas, APU Gemini) | B3: 0.5 | C3: 12490 | D3: - | E3: - | F3: - | G3: -
A4: Plan Pro IA ($19.990 - $29.990 / WhatsApp Bot, Gemini Pro) | B4: 0.5 | C4: 24990 | D4: - | E4: - | F4: - | G4: -
A5: Precio Mensual Promedio Ponderado por Cliente (CLP) | B5: 1 | C5: =B3*C3+B4*C4 -> 18740 | D5: =C5 -> 18740 | E5: =D5*(1+'1. Supuestos & Macro'!C8) -> 19452 | F5: =E5*(1+'1. Supuestos & Macro'!C8) -> 20191 | G5: =F5*(1+'1. Supuestos & Macro'!C8) -> 20959
A7: Proyección de Clientes Activos (Suscripciones) | C7: Unidad | D7: Año 1 (2027) | E7: Año 2 (2028) | F7: Año 3 (2029) | G7: Año 4 (2030)
A8: Usuarios Activos Plan Gratis (Funnel Freemium) | C8: PYMEs | D8: 300 | E8: 750 | F8: 1400 | G8: 2200
A9: Clientes Plan Pro (50% de pago) | C9: PYMEs | D9: =ROUND(D11*B3,0) -> 48 | E9: =ROUND(E11*B3,0) -> 105 | F9: =ROUND(F11*B3,0) -> 190 | G9: =ROUND(G11*B3,0) -> 290
A10: Clientes Plan Pro IA (50% de pago) | C10: PYMEs | D10: =ROUND(D11*B4,0) -> 47 | E10: =ROUND(E11*B4,0) -> 105 | F10: =ROUND(F11*B4,0) -> 190 | G10: =ROUND(G11*B4,0) -> 290
A11: Total Clientes Activos de Pago (Cartera Anual) | C11: PYMEs | D11: 95 | E11: 210 | F11: 380 | G11: 580
A13: Ingresos Operacionales Proyectados (CLP) | D13: Año 1 (2027) | E13: Año 2 (2028) | F13: Año 3 (2029) | G13: Año 4 (2030)
A14: Total Facturación Anual Neta SaaS (CLP) | D14: =D11*D5*12 -> 21363600 | E14: =E11*E5*12 -> 49019342 | F14: =F11*F5*12 -> 92072331 | G14: =G11*G5*12 -> 145871647
A16: ANÁLISIS DE PUNTO DE EQUILIBRIO OPERACIONAL (BREAK-EVEN) | D16: Año 1 (2027) | E16: Año 2 (2028) | F16: Año 3 (2029) | G16: Año 4 (2030)
A17: Costos Fijos Operativos Anuales (CLP) | D17: ='10. Flujo Neto de Fondos'!C6+'10. Flujo Neto de Fondos'!C7+'10. Flujo Neto de Fondos'!C8 -> 19733930 | E17: ='10. Flujo Neto de Fondos'!D6+'10. Flujo Neto de Fondos'!D7+'10. Flujo Neto de Fondos'!D8 -> 30383866 | F17: ='10. Flujo Neto de Fondos'!E6+'10. Flujo Neto de Fondos'!E7+'10. Flujo Neto de Fondos'!E8 -> 42460514 | G17: ='10. Flujo Neto de Fondos'!F6+'10. Flujo Neto de Fondos'!F7+'10. Flujo Neto de Fondos'!F8 -> 49754000
A18: Margen de Contribución Unitario Anual por Cliente (CLP) | D18: =D5*12*(1-'1. Supuestos & Macro'!C18-'1. Supuestos & Macro'!C19)-('10. Flujo Neto de Fondos'!C3/D11) -> 197358 | E18: =E5*12*(1-'1. Supuestos & Macro'!C18-'1. Supuestos & Macro'!C19)-('10. Flujo Neto de Fondos'!D3/E11) -> 204684 | F18: =F5*12*(1-'1. Supuestos & Macro'!C18-'1. Supuestos & Macro'!C19)-('10. Flujo Neto de Fondos'!E3/F11) -> 212450 | G18: =G5*12*(1-'1. Supuestos & Macro'!C18-'1. Supuestos & Macro'!C19)-('10. Flujo Neto de Fondos'!F3/G11) -> 220530
A19: Punto de Equilibrio en Clientes Activos (Q* = CF / MCU) | C19: Clientes | D19: =ROUNDUP(D17/D18, 0) -> 100 | E19: =ROUNDUP(E17/E18, 0) -> 148 | F19: =ROUNDUP(F17/F18, 0) -> 200 | G19: =ROUNDUP(G17/G18, 0) -> 226
A20: Estado Frente al Punto de Equilibrio | C20: Condición | D20: Fase de Adopción (95 Clientes) | E20: Superado en Año 2 (210 Clientes) | F20: Superado Ampliamente | G20: Madurez y Alta Rentabilidad

Sheet 8. Inversion & Cap Trabajo
A1: Categoría de Inversión | B1: Detalle del Ítem Invertido | C1: Monto Inversión (CLP) | D1: Fuente / Referencia de Hoja | E1: Destino / Rol Estratégico
A2: Activos Fijos (Físicos) | B2: Equipamiento Computacional Año 0 (PC + Notebook) | C2: 1800000 | D2: Hoja 3. Maquinaria | E2: Hardware de desarrollo y arquitectura
A3: Activos Fijos (Físicos) | B3: Smartphone Android Test Terreno (Samsung A35) | C3: 180000 | D3: Hoja 3. Maquinaria | E3: Pruebas WhatsApp Cloud API y GPS
A4: Activos Fijos (Físicos) | B4: Monitores 27" IPS para Estaciones (2 Monitores) | C4: 300000 | D4: Hoja 3. Maquinaria | E4: Productividad y programación paralela
A5: Subtotal Activos Fijos | B5: Total Inversión Física Tangible en Año 0 | C5: =SUM(C2:C4) -> 2280000 | D5: - | E5: Depreciable tributariamente según SII
A6: Activos Intangibles | B6: Constitución Legal de Sociedad SpA (Firma, Notaría) | C6: 180000 | D6: Hoja 6. Gastos Gen | E6: Formalización jurídica de ObraTrack SpA
A7: Activos Intangibles | B7: Registro de Marca ObraTrack en INAPI (Clases 9 y 42) | C7: 320000 | D7: Hoja 6. Gastos Gen | E7: Protección intelectual de marca y software
A8: Activos Intangibles | B8: Software & Licencias de Desarrollo Año 0 | C8: ='4. Software & Licencias'!D11 -> 585510 | D8: Hoja 4. Software | E8: Google AI Pro, Movistar, Dominio, GitHub, etc.
A9: Subtotal Activos Intangibles | B9: Total Inversión Intangible Pre-operativa | C9: =SUM(C6:C8) -> 1085510 | D9: - | E9: Activo nominal amortizable
A10: Capital de Trabajo (KT) | B10: Mano de Obra 2 Fundadores en Año 0 (6 Meses) | C10: ='2. Mano de Obra'!F5 -> 8778000 | D10: Hoja 2. Mano de Obra | E10: Sueldos pre-operativos de los 2 fundadores
A11: Capital de Trabajo (KT) | B11: Fondo de Cobertura de Operación Inicial (Reserva Caja) | C11: 3000000 | D11: Reserva de Liquidez | E11: Cobertura de desfase de ingresos Año 1
A12: Subtotal Capital de Trabajo | B12: Total Capital de Trabajo Requerido (KT) | C12: =SUM(C10:C11) -> 11778000 | D12: - | E12: Recuperable al 100% en Año 4
A13: TOTAL INVERSIÓN INICIAL (AÑO 0) | B13: Inversión Total Previa a Puesta en Marcha | C13: =C5+C9+C12 -> 15143510 | D13: - | E13: Financiamiento Total Requerido para Iniciar

Sheet 9. Personal Operativo
A1: Cargo Operacional | B1: Modalidad / Tipo Contrato | C1: Año 1 (2027) | D1: Año 2 (2028) | E1: Año 3 (2029) | F1: Año 4 (2030) | G1: Funciones Clave en Operación
A2: Fundador 1: Jefe de Proyecto & CTO | B2: Indefinido (Jornada Completa) | C2: ='2. Mano de Obra'!G9 -> 8151000 | D2: ='2. Mano de Obra'!H9 -> 10032000 | E2: ='2. Mano de Obra'!I9 -> 11913000 | F2: ='2. Mano de Obra'!J9 -> 14421000 | G2: Dirección general, arquitectura Next.js y APIs
A3: Fundador 2: Desarrollador Full-Stack Senior | B3: Indefinido (Jornada Completa) | C3: ='2. Mano de Obra'!G10 -> 8151000 | D3: ='2. Mano de Obra'!H10 -> 10032000 | E3: ='2. Mano de Obra'!I10 -> 11913000 | F3: ='2. Mano de Obra'!J10 -> 14421000 | G3: Desarrollo web, base de datos Supabase y DevOps
A4: Soporte Técnico & Onboarding Terreno (Año 2) | B4: Indefinido (Onboarding y WhatsApp) | C4: ='2. Mano de Obra'!G11 -> 0 | D4: ='2. Mano de Obra'!H11 -> 6270000 | E4: ='2. Mano de Obra'!I11 -> 6897000 | F4: ='2. Mano de Obra'!J11 -> 7524000 | G4: Capacitación a capataces y soporte cuadrillas
A5: Ejecutivo Comercial B2B (Año 3) | B5: Indefinido (Base + Leyes) | C5: ='2. Mano de Obra'!G12 -> 0 | D5: ='2. Mano de Obra'!H12 -> 0 | E5: ='2. Mano de Obra'!I12 -> 6897000 | F5: ='2. Mano de Obra'!J12 -> 7524000 | G5: Prospección en constructoras y ferias de construcción
A6: Comisiones Comerciales por Ventas (5%) | B6: Variable (% sobre Ventas Netas) | C6: ='7. Demanda & Ingresos'!D14*'1. Supuestos & Macro'!C19 -> 1068180 | D6: ='7. Demanda & Ingresos'!E14*'1. Supuestos & Macro'!C19 -> 2450967 | E6: ='7. Demanda & Ingresos'!F14*'1. Supuestos & Macro'!C19 -> 4603617 | F6: ='7. Demanda & Ingresos'!G14*'1. Supuestos & Macro'!C19 -> 7293582 | G6: 5% de incentivo por ventas netas facturadas
A7: Total Costo Personal Operativo & Ventas (CLP) | B7: - | C7: =SUM(C2:C6) -> 17370180 | D7: =SUM(D2:D6) -> 28784967 | E7: =SUM(E2:E6) -> 42223617 | F7: =SUM(F2:F6) -> 51183582 | G7: Mano de Obra Fase Operativa

Sheet 10. Flujo Neto de Fondos
A1: Ítem del Flujo de Fondos (CLP) | B1: Año 0 (2026) | C1: Año 1 (2027) | D1: Año 2 (2028) | E1: Año 3 (2029) | F1: Año 4 (2030) | G1: Referencia / Fórmula
A2: (+) Ingresos Operacionales por Suscripciones SaaS | B2: 0 | C2: ='7. Demanda & Ingresos'!D14 -> 21363600 | D2: ='7. Demanda & Ingresos'!E14 -> 49019342 | E2: ='7. Demanda & Ingresos'!F14 -> 92072331 | F2: ='7. Demanda & Ingresos'!G14 -> 145871647 | G2: Hoja 7. Demanda & Ingresos
A3: (-) Costos Variables Cloud & APIs | B3: 0 | C3: ='5. Infraestructura Cloud'!C6 -> 996000 | D3: ='5. Infraestructura Cloud'!D6 -> 2450000 | E3: ='5. Infraestructura Cloud'!E6 -> 4840000 | F3: ='5. Infraestructura Cloud'!F6 -> 7940000 | G3: Hoja 5. Infraestructura Cloud
A4: (-) Comisiones Pasarela de Pago (2.5% Ventas) | B4: 0 | C4: =C2*'1. Supuestos & Macro'!C18 -> 534090 | D4: =D2*'1. Supuestos & Macro'!C18 -> 1225484 | E4: =E2*'1. Supuestos & Macro'!C18 -> 2301808 | F4: =F2*'1. Supuestos & Macro'!C18 -> 3646791 | G4: 2.5% arancel Transbank Webpay Plus
A5: (-) Comisiones Equipo Comercial (5% Ventas) | B5: 0 | C5: ='9. Personal Operativo'!C6 -> 1068180 | D5: ='9. Personal Operativo'!D6 -> 2450967 | E5: ='9. Personal Operativo'!E6 -> 4603617 | F5: ='9. Personal Operativo'!F6 -> 7293582 | G5: Hoja 9. Personal Operativo
A6: (-) Costos Fijos de Personal Operativo (Sueldos) | B6: 0 | C6: ='2. Mano de Obra'!G13 -> 16302000 | D6: ='2. Mano de Obra'!H13 -> 26334000 | E6: ='2. Mano de Obra'!I13 -> 37620000 | F6: ='2. Mano de Obra'!J13 -> 43890000 | G6: Hoja 2. Mano de Obra Operativa
A7: (-) Insumos, Oficina Virtual & Contador | B7: 0 | C7: ='6. Insumos & Gastos Gen'!D8 -> 2148000 | D7: ='6. Insumos & Gastos Gen'!E8 -> 2502264 | E7: ='6. Insumos & Gastos Gen'!F8 -> 2858590 | F7: ='6. Insumos & Gastos Gen'!G8 -> 3277056 | G7: Hoja 6. Gastos Generales
A8: (-) Software & Licencias de Producción | B8: 0 | C8: ='4. Software & Licencias'!E11 -> 1283930 | D8: ='4. Software & Licencias'!F11 -> 1547602 | E8: ='4. Software & Licencias'!G11 -> 1981924 | F8: ='4. Software & Licencias'!H11 -> 2586944 | G8: Hoja 4. Licencias TI
A9: (-) Depreciación Maquinaria & Equipos | B9: 0 | C9: ='3. Maquinaria & Equipos'!D15 -> 1002500 | D9: ='3. Maquinaria & Equipos'!E15 -> 1002500 | E9: ='3. Maquinaria & Equipos'!F15 -> 855000 | F9: ='3. Maquinaria & Equipos'!G15 -> 225000 | G9: Hoja 3. Depreciación SII
A10: (=) UTILIDAD ANTES DE IMPUESTOS (UAI) | B10: 0 | C10: =C2-SUM(C3:C9) -> -1971100 | D10: =D2-SUM(D3:D9) -> 11506525 | E10: =E2-SUM(E3:E9) -> 37011392 | F10: =F2-SUM(F3:F9) -> 77012274 | G10: Ingresos - Costos y Gastos
A11: (-) Impuesto a la Renta de 1ª Categoría (27%) | B11: 0 | C11: =IF(C10>0, C10*'1. Supuestos & Macro'!C9, 0) -> 0 | D11: =IF(D10>0, D10*'1. Supuestos & Macro'!C9, 0) -> 3106762 | E11: =IF(E10>0, E10*'1. Supuestos & Macro'!C9, 0) -> 9993076 | F11: =IF(F10>0, F10*'1. Supuestos & Macro'!C9, 0) -> 20793314 | G11: SII 27% (si UAI > 0)
A12: (=) UTILIDAD DESPUÉS DE IMPUESTOS (UDI) | B12: 0 | C12: =C10-C11 -> -1971100 | D12: =D10-D11 -> 8399763 | E12: =E10-E11 -> 27018316 | F12: =F10-F11 -> 56218960 | G12: UAI - Impuestos
A13: (+) Ajuste por Depreciación (Gasto No Desembolsable) | B13: 0 | C13: =C9 -> 1002500 | D13: =D9 -> 1002500 | E13: =E9 -> 855000 | F13: =F9 -> 225000 | G13: Reverso gasto contable
A14: (-) Inversión Activos Fijos e Intangibles | B14: =-'8. Inversion & Cap Trabajo'!C5-'8. Inversion & Cap Trabajo'!C9 -> -3365510 | C14: =-'3. Maquinaria & Equipos'!E10 -> -900000 | D14: 0 | E14: 0 | F14: 0 | G14: Año 0 Físico/Intangible + Año 1 Equipos
A15: (-) Inversión en Capital de Trabajo | B15: =-'8. Inversion & Cap Trabajo'!C12 -> -11778000 | C15: 0 | D15: 0 | E15: 0 | F15: 0 | G15: Año 0 2 Fundadores + Reserva
A16: (+) Recuperación de Capital de Trabajo | B16: 0 | C16: 0 | D16: 0 | E16: 0 | F16: ='8. Inversion & Cap Trabajo'!C12 -> 11778000 | G16: Fin horizonte Año 4 (100% liberado)
A17: (+) Valor de Salvamento / Desecho de Activos | B17: 0 | C17: 0 | D17: 0 | E17: 0 | F17: ='3. Maquinaria & Equipos'!I15 -> 320000 | G17: Valor residual en mercado Año 4
A18: (=) FLUJO NETO DE FONDOS (FNF / CASH FLOW) | B18: =B14+B15 -> -15143510 | C18: =C12+C13+C14+C15+C16+C17 -> -1868600 | D18: =D12+D13+D14+D15+D16+D17 -> 9402263 | E18: =E12+E13+E14+E15+E16+E17 -> 27873316 | F18: =F12+F13+F14+F15+F16+F17 -> 68541960 | G18: Flujo de Caja Libre Neto
A20: INDICADORES FINANCIEROS DE EVALUACIÓN ECONÓMICA | G20: CRITERIO DE DECISIÓN
A21: Tasa de Descuento del Proyecto (CAPM - Ke) | B21: ='1. Supuestos & Macro'!C15 -> 0.1285 | G21: Tasa exigida por riesgo del sector TI (11% - 15%)
A22: Valor Actual Neto (VAN / NPV) | B22: =NPV(B21, C18:F18) + B18 -> 52240363 | G22: VAN > 0 : Proyecto Altamente Rentable y Viable
A23: Tasa Interna de Retorno (TIR / IRR) | B23: =IRR(B18:F18) -> 0.7284 | G23: TIR > Ke : Retorno supera holgadamente el costo de capital
A24: Período de Recuperación de Inversión (PRI Simple) | B24: Año 3 (Mes 3) | G24: Recuperación total de inversión durante el 3er año
A25: Retorno sobre la Inversión (ROI Acumulado) | B25: =(SUM(C18:F18)+B18)/(-B18) -> 5.86 | G25: ROI > 500% generado en el horizonte de 4 años
A27: Flujo Acumulado para Cálculo de Payback (PRI) | B27: Año 0 (2026) | C27: Año 1 (2027) | D27: Año 2 (2028) | E27: Año 3 (2029) | F27: Año 4 (2030) | G27: Estado de Recuperación
A28: Flujo Neto Acumulado (CLP) | B28: =B18 -> -15143510 | C28: =B28+C18 -> -17012110 | D28: =C28+D18 -> -7609846 | E28: =D28+E18 -> 20263470 | F28: =E28+F18 -> 88805429 | G28: Inversión Recuperada con Holgura en Año 3
A30: ANÁLISIS DE SENSIBILIDAD POR ESCENARIO | B30: Variación Demanda | C30: VAN Estimado (CLP) | D30: TIR Estimada (%) | E30: PRI Estimado | F30: Resultado | G30: Estrategia de Mitigación
A31: Escenario Pesimista (-20% Demanda / Clientes) | B31: -20.0% | C31: 25120000 | D31: 0.458 | E31: Año 3 (Mes 8) | F31: Altamente Rentable | G31: Ajuste de presupuesto publicitario y foco en retención de contratistas
A32: Escenario Base (Proyección Normal ObraTrack) | B32: 0.0% | C32: =B22 -> 52240363 | D32: =B23 -> 0.7284 | E32: Año 3 (Mes 3) | F32: Excepcional Rentabilidad y Viabilidad | G32: Ejecución del plan comercial estándar en Región Metropolitana
A33: Escenario Optimista (+20% Demanda / Clientes) | B33: +20.0% | C33: 79250000 | D33: 0.992 | E33: Año 2 (Mes 10) | F33: Máxima Rentabilidad | G33: Aceleración de cuadrillas y expansión a mercados de Perú/Colombia
